HaveFun/__init__.py
HaveFun/common.py
HaveFun/vision.py
HaveFun-1.0.3.dist-info/COPYING.txt
HaveFun-1.0.3.dist-info/METADATA
HaveFun-1.0.3.dist-info/WHEEL
HaveFun-1.0.3.dist-info/top_level.txt
HaveFun-1.0.3.dist-info/zip-safe
HaveFun-1.0.3.dist-info/RECORD
